{"cameraMode":{"drawMode":0,"name":"Shaded","section":"Shading Mode"},"sceneLighting":true,"audioPlay":false,"sceneViewState":{"m_AlwaysRefresh":false,"showFog":true,"showSkybox":true,"showFlares":true,"showImageEffects":true,"showParticleSystems":true,"showVisualEffectGraphs":true,"m_FxEnabled":true},"in2DMode":false,"pivot":{"x":141.13800048828126,"y":-22.854999542236329,"z":105.80799865722656},"rotation":{"x":-0.0008753829170018435,"y":0.995308518409729,"z":-0.09795306622982025,"w":-0.008043180219829083},"size":1.1102349758148194,"orthographic":false}